LICENSE
pyle_on/__init__.py
pyle_on-0.1.0.dist-info/LICENSE
pyle_on-0.1.0.dist-info/WHEEL
pyle_on-0.1.0.dist-info/METADATA
pyle_on-0.1.0.dist-info/RECORD
